scalapack4py/__init__.py
scalapack4py/array_types.py
scalapack4py/blacsdesc.py
scalapack4py/func_argtypes.py
scalapack4py/scalapack4py.py
scalapack4py/scalapackfunc_prototype.py
scalapack4py/npscal/__init__.py
scalapack4py/npscal/blacs_ctxt_management.py
scalapack4py/npscal/comms.py
scalapack4py/npscal/npscal.py
scalapack4py/npscal/utils.py
scalapack4py/npscal/index_utils/npscal_select.py
scalapack4py/npscal/math_utils/npscal2npscal.py
scalapack4py/npscal/math_utils/operations.py
scalapack4py-0.2.1.dist-info/licenses/LICENSE
scalapack4py-0.2.1.dist-info/METADATA
scalapack4py-0.2.1.dist-info/WHEEL
scalapack4py-0.2.1.dist-info/top_level.txt
scalapack4py-0.2.1.dist-info/RECORD
