Metadata-Version: 2.4
Name: scalapack4py
Version: 0.2.1
Summary: Python wrapper for dynamically loaded ScaLAPACK and BLACS libraries
Author-email: Pavel Stishenko <pstishenko@gmail.com>, Gabriel Bramley <BramleyG@cardiff.ac.uk>
License: MIT License
Project-URL: Homepage, https://gitlab.com/pvst/scalapack4py
Project-URL: Bug Tracker, https://gitlab.com/pvst/scalapack4py/-/issues
Classifier: Programming Language :: Python :: 3
Classifier: License :: OSI Approved :: MIT License
Classifier: Operating System :: OS Independent
Requires-Python: >=3.7
License-File: LICENSE
Requires-Dist: mpi4py>=3.1.3
Requires-Dist: numpy>=2.0.0
Dynamic: license-file
